_lever_utils/__init__.py
_lever_utils/foo/__init__.py
_lever_utils/foo/helpers/__init__.py
_lever_utils/foo/helpers/alarm/__init__.py
_lever_utils/foo/helpers/alarm/dingding.py
_lever_utils/foo/helpers/db/__init__.py
_lever_utils/foo/helpers/db/es_helper.py
_lever_utils/foo/helpers/db/hive_helper.py
_lever_utils/foo/helpers/db/impala_helper.py
_lever_utils/foo/helpers/db/mysql_helper.py
_lever_utils/foo/helpers/db/redis_helper.py
_lever_utils/foo/helpers/file/__init__.py
_lever_utils/foo/helpers/file/excel_helper.py
_lever_utils/foo/helpers/file/oss_helper.py
_lever_utils/foo/helpers/mail/__init__.py
_lever_utils/foo/helpers/mail/mail_helper.py
_lever_utils/foo/helpers/mail/mail_helper_test.py
_lever_utils/foo/helpers/time/__init__.py
1lever_utils-0.1.8.dist-info/LICENSE
1lever_utils-0.1.8.dist-info/METADATA
1lever_utils-0.1.8.dist-info/WHEEL
1lever_utils-0.1.8.dist-info/top_level.txt
1lever_utils-0.1.8.dist-info/RECORD
