Metadata-Version: 2.1
Name: 1lever-utils
Version: 0.1.8
Summary: utils
Home-page: https://github.com/0lever/utils
Author: fqiyou
Author-email: yc.fqiyou@gmail.com
License: UNKNOWN
Platform: UNKNOWN
Requires-Dist: aliyun-python-sdk-core
Requires-Dist: aliyun-python-sdk-kms
Requires-Dist: asn1crypto
Requires-Dist: bcrypt
Requires-Dist: bit-array
Requires-Dist: bitarray
Requires-Dist: cffi
Requires-Dist: chardet
Requires-Dist: crcmod
Requires-Dist: cryptography
Requires-Dist: DateTime
Requires-Dist: elasticsearch (==6.3.1)
Requires-Dist: enum34
Requires-Dist: greenlet
Requires-Dist: idna
Requires-Dist: impyla
Requires-Dist: ipaddress
Requires-Dist: jmespath
Requires-Dist: numpy
Requires-Dist: oss2
Requires-Dist: pandas
Requires-Dist: paramiko
Requires-Dist: pyasn1
Requires-Dist: PyMySQL
Requires-Dist: PyNaCl
Requires-Dist: python-dateutil
Requires-Dist: pytz
Requires-Dist: redis
Requires-Dist: requests
Requires-Dist: sasl (==0.2.1)
Requires-Dist: six
Requires-Dist: SQLAlchemy
Requires-Dist: sshtunnel
Requires-Dist: thrift (==0.9.3)
Requires-Dist: thrift-sasl (==0.3.0)
Requires-Dist: urllib3
Requires-Dist: zope.interface
